[
  {
    "name": "apricorn",
    "blocks": [
      "cobblemon:red_apricorn",
      "cobblemon:yellow_apricorn",
      "cobblemon:green_apricorn",
      "cobblemon:blue_apricorn",
      "cobblemon:pink_apricorn",
      "cobblemon:black_apricorn",
      "cobblemon:white_apricorn"
    ]
  },
  {
    "name": "Ores",
    "blocks": [
      "minecraft:coal_ore",
      "minecraft:deepslate_coal_ore",
      "minecraft:copper_ore",
      "minecraft:deepslate_copper_ore",
      "minecraft:diamond_ore",
      "minecraft:deepslate_diamond_ore",
      "minecraft:emerald_ore",
      "minecraft:deepslate_emerald_ore",
      "minecraft:gold_ore",
      "minecraft:deepslate_gold_ore",
      "minecraft:iron_ore",
      "minecraft:deepslate_iron_ore",
      "minecraft:lapis_ore",
      "minecraft:deepslate_lapis_ore",
      "minecraft:redstone_ore",
      "minecraft:deepslate_redstone_ore",
      "minecraft:nether_gold_ore",
      "minecraft:nether_quartz_ore",
      "cobblemon:fire_stone_ore",
      "cobblemon:deepslate_fire_stone_ore",
      "cobblemon:nether_fire_stone_ore",
      "mega_showdown:mega_meteorid_fire_ore",
      "cobblemon:water_stone_ore",
      "cobblemon:deepslate_water_stone_ore",
      "mega_showdown:mega_meteorid_water_ore",
      "cobblemon:thunder_stone_ore",
      "cobblemon:deepslate_thunder_stone_ore",
      "mega_showdown:mega_meteorid_thunder_ore",
      "cobblemon:leaf_stone_ore",
      "cobblemon:deepslate_leaf_stone_ore",
      "mega_showdown:mega_meteorid_leaf_ore",
      "cobblemon:moon_stone_ore",
      "cobblemon:deepslate_moon_stone_ore",
      "cobblemon:dripstone_moon_stone_ore",
      "mega_showdown:mega_meteorid_moon_ore",
      "cobblemon:sun_stone_ore",
      "cobblemon:deepslate_sun_stone_ore",
      "cobblemon:terracotta_sun_stone_ore",
      "mega_showdown:mega_meteorid_sun_ore",
      "cobblemon:shiny_stone_ore",
      "cobblemon:deepslate_shiny_stone_ore",
      "mega_showdown:mega_meteorid_shiny_ore",
      "cobblemon:dusk_stone_ore",
      "cobblemon:deepslate_dusk_stone_ore",
      "mega_showdown:mega_meteorid_dusk_ore",
      "cobblemon:dawn_stone_ore",
      "cobblemon:deepslate_dawn_stone_ore",
      "mega_showdown:mega_meteorid_dawn_ore",
      "cobblemon:ice_stone_ore",
      "cobblemon:deepslate_ice_stone_ore",
      "mega_showdown:mega_meteorid",
      "mega_showdown:keystone_ore"
    ],
    "tools": [
      "minecraft:wooden_pickaxe",
      "minecraft:stone_pickaxe",
      "minecraft:golden_pickaxe",
      "minecraft:copper_pickaxe",
      "minecraft:iron_pickaxe",
      "minecraft:diamond_pickaxe",
      "minecraft:netherite_pickaxe",
      "hanas_paxel_mod:wood_paxel",
      "hanas_paxel_mod:stone_paxel",
      "hanas_paxel_mod:iron_paxel",
      "hanas_paxel_mod:diamond_paxel",
      "hanas_paxel_mod:golden_paxel",
      "hanas_paxel_mod:netherite_paxel"
    ]
  },
  {
    "name": "Wood",
    "blocks": [
      "minecraft:oak_log",
      "minecraft:spruce_log",
      "minecraft:birch_log",
      "minecraft:jungle_log",
      "minecraft:acacia_log",
      "minecraft:dark_oak_log",
      "minecraft:mangrove_log",
      "minecraft:cherry_log",
      "minecraft:pale_oak_log",
      "minecraft:crimson_stem",
      "minecraft:warped_stem",
      "cobblemon:apricorn_log",
      "cobblemon:saccharine_log"
    ],
    "tools": [
      "minecraft:wooden_axe",
      "minecraft:stone_axe",
      "minecraft:golden_axe",
      "minecraft:copper_axe",
      "minecraft:iron_axe",
      "minecraft:diamond_axe",
      "minecraft:netherite_axe",
      "hanas_paxel_mod:wood_paxel",
      "hanas_paxel_mod:stone_paxel",
      "hanas_paxel_mod:iron_paxel",
      "hanas_paxel_mod:diamond_paxel",
      "hanas_paxel_mod:golden_paxel",
      "hanas_paxel_mod:netherite_paxel"
    ]
  }
]